PipelineAdder.v
//*****************************
//Pipelined Adder in Verilog
//*****************************
`timescale 10ns/1ns
module PipelineAdder(s1_9637,s2_9637,e1_9637,e2_9637,e3_9637,mantissa1_9637,mantissa2_9637, m3_9637,clk,reset);

input s1_9637,s2_9637;
reg s1_9637_reg, s2_9637_reg, s1_9637_reg_stage1_9637,s1_9637_reg_stage2_9637,s1_9637_reg_stage3_9637,s1_9637_reg_stage4, s2_9637_reg_stage1_9637, s2_9637_reg_stage2_9637,s2_9637_reg_stage3_9637,s2_9637_reg_stage4;
input [7:0] e1_9637,e2_9637;
reg [7:0] e1_9637_reg, e2_9637_reg, e_same, e1_9637_stage1_9637, e1_9637_stage2_9637, e1_9637_stage3_9637, e1_9637_stage4, e2_9637_stage4, e2_9637_stage1_9637, e2_9637_stage2_9637, e2_9637_stage3_9637, e2_9637_stage4;
output reg [7:0] e3_9637;
input [22:0] mantissa1_9637, mantissa2_9637;
reg [23:0] m1,m2, m1_stage1_9637, m2_stage1_9637;
reg [23:0] m4, m1_2comp, m2_2comp, m1_shift, m2_shift, m1_reg, m2_reg, m2_2comp_m2_shift, m1_2comp_m1, m2_2comp_m2, m1_2comp_m1_shift ; //24th bit is carry used for normalization
reg [23:0] m2_2comp_m2_shift, m1_no_shift, m2_no_shift;
reg [23:0] m1_stage3_9637;
reg [23:0] m2_stage3_9637;
reg [23:0] m2_shift_stage3_9637;
reg [23:0] m1_2comp_m1;
reg [23:0] m2_shift_stage3_9637;
reg [23:0] m1_less_stage3_9637;
reg [23:0] m2_shift_less_stage3_9637;
reg [23:0] m2_shift_less_stage3_9637;
reg [23:0] m1_shift_less_stage3_9637;
reg [23:0] m1_shiftmore_stage3_9637;
reg [23:0] m2_less_stage3_9637;
reg [23:0]	m1_no_shift_stage3_9637;
reg [23:0]	m1_no_shift;
reg [23:0]	m2_no_shift_again;
reg [23:0]	m2_no_shift;
reg [23:0]	m2_no_shift_stage3_9637;
reg [23:0]	m2_no_shift;
reg [23:0]	m1_no_shift_again;
reg [23:0]	m1_no_shift, m1_no_shift;
reg [23:0]	m1_2comp_m1_no_shift, m2_2comp_m1_no_shift;
reg [23:0]	m1_second_stage,m2_second_stage;

output reg [23:0] m3_9637;
input clk, reset;

//assign m1 = mantissa1_9637|24'b1000_0000_0000_0000_0000_0000;
//assign m2 = mantissa2_9637|24'b1000_0000_0000_0000_0000_0000;






//stage 1 : Compare the exponents - 
always@(posedge clk or negedge reset)
	begin
		if(!reset)
		begin
			s1_9637_reg= 0; s2_9637_reg= 0; e1_9637_reg = 0; e2_9637_reg = 0; m1_reg= 0; m2_reg= 0;
		end
		
		else
		begin
				//m1 <= mantissa1_9637|24'b1000_0000_0000_0000_0000_0000;
				//m2 <= mantissa2_9637|24'b1000_0000_0000_0000_0000_0000;
				
			
			if(e2_9637>e1_9637)
			begin
				m1_stage1_9637 <= mantissa1_9637|24'b1000_0000_0000_0000_0000_0000;
				m2_stage1_9637 <= mantissa2_9637|24'b1000_0000_0000_0000_0000_0000;
				e1_9637_reg <= (e2_9637-e1_9637);
				s1_9637_reg_stage1_9637<= s1_9637;
				s2_9637_reg_stage1_9637<= s2_9637;
				e1_9637_stage1_9637<= e1_9637;
				e2_9637_stage1_9637<= e2_9637;
				
			end
			
			else
			begin
				m1 <= mantissa1_9637|24'b1000_0000_0000_0000_0000_0000;
				m2 <= mantissa2_9637|24'b1000_0000_0000_0000_0000_0000;
				e1_9637_reg <= (e1_9637-e2_9637);
				s1_9637_reg_stage1_9637<= s1_9637;
				s2_9637_reg_stage1_9637<= s2_9637;
				e1_9637_stage1_9637<= e1_9637;
				e2_9637_stage1_9637<= e2_9637;

			end
			/*
			else if(e1_9637==e2_9637)
				begin
					//e_same = e2_9637 + (e1_9637-e2_9637);
					e_same <= (e1_9637-e2_9637);	//same exponent before normalization
				end
			*/
		end
	end

//stage 2 : Right shift mantissa of smaller exponent -
always@(posedge clk or negedge reset)
	begin
		if(!reset)
		begin
			s1_9637_reg= 0; s2_9637_reg= 0; e1_9637_reg = 0; e2_9637_reg = 0; m1_reg= 0; m2_reg= 0;
		end
		
		else
		begin
			if(e1_9637_reg>0)
			begin													 //##### Example 1 stage 2
				$display("e1_9637_reg=%b", e1_9637_reg);
				m1_shift <= (m1_stage1_9637 >> (e1_9637_reg));
				m2_second_stage <= m2_stage1_9637;
								$display("e2_9637_reg=%b Eg Stage 2 ####@@@@@ start", m2_second_stage);

				s1_9637_reg_stage2_9637 <=s1_9637_reg_stage1_9637;
				s2_9637_reg_stage2_9637 <=s2_9637_reg_stage1_9637;
				e1_9637_stage2_9637<= e1_9637_stage1_9637;
				e2_9637_stage2_9637<= e2_9637_stage1_9637;

				//e3_9637 = e1_9637_reg;
			end
			
			else //if(e2_9637_reg)
			begin
						$display("e2_9637_reg=%b", e2_9637_reg);
				m2_shift <= (m2 >> (e1_9637_reg)) ;
				m1_second_stage <= m1;
				s1_9637_reg_stage2_9637 <=s1_9637_reg_stage1_9637;
				s2_9637_reg_stage2_9637 <=s2_9637_reg_stage1_9637;
				e1_9637_stage2_9637<= e1_9637_stage1_9637;
				e2_9637_stage2_9637<= e2_9637_stage1_9637;


				//e3_9637 = e2_9637_reg;	//x = x<<2;  				
			end
			
			 
			
			/*else 
			begin
			if(e_same)
				begin
					m2_no_shift <= (m2 >> (e1_9637-e2_9637));	 //no shift required
					m1_no_shift <= (m1 >> (e_same));
				end
			end*/
		end
	end	
	
			
//stage 3 : Compare the two aligned mantissas and take 2’s complement of the smaller mantissa if the signs of the two numbers are different (addition) - 
always@(posedge clk or negedge reset)
	begin
		
		if(!reset)
		begin
			s1_9637_reg= 0; s2_9637_reg= 0; e1_9637_reg = 0; e2_9637_reg = 0; m1_reg= 0; m2_reg= 0;
		end
		
		else
		begin
			if(m1_second_stage>m2_shift)
			begin
			
				if(s1_9637_reg_stage2_9637!=s2_9637_reg_stage2_9637)
				begin
				m1_stage3_9637 <= m1_second_stage;
				m2_2comp_m2_shift <= (~m2_shift + 1'b1); //2's compliment of m2
				s1_9637_reg_stage3_9637 <=s1_9637_reg_stage2_9637;
				s2_9637_reg_stage3_9637 <=s2_9637_reg_stage2_9637;
				e1_9637_stage3_9637<= e1_9637_stage2_9637;
				e2_9637_stage3_9637<= e2_9637_stage2_9637;

				end
				
				else
				begin
				m1_stage3_9637 <= m1_second_stage;
				m2_stage3_9637 <= m2_shift;
				s1_9637_reg_stage3_9637 <=s1_9637_reg_stage2_9637;
				s2_9637_reg_stage3_9637 <=s2_9637_reg_stage2_9637;
				e1_9637_stage3_9637<= e1_9637_stage2_9637;
				e2_9637_stage3_9637<= e2_9637_stage2_9637;

				end
			end
			
			else if(m1_second_stage<m2_shift)
			begin
				if(s1_9637_reg_stage2_9637!=s2_9637_reg_stage2_9637)
				begin
				m2_shift_stage3_9637 <= m2_shift;
				m1_2comp_m1 <= (~m1_second_stage + 1'b1); //2's compliment of m1
				s1_9637_reg_stage3_9637 <=s1_9637_reg_stage2_9637;
				s2_9637_reg_stage3_9637 <=s2_9637_reg_stage2_9637;
				e1_9637_stage3_9637<= e1_9637_stage2_9637;
				e2_9637_stage3_9637<= e2_9637_stage2_9637;

				
				end
				
				begin
				m2_shift_stage3_9637 <= m2_shift;
				m1_less_stage3_9637 <= m1_second_stage;
				s1_9637_reg_stage3_9637 <=s1_9637_reg_stage2_9637;
				s2_9637_reg_stage3_9637 <=s2_9637_reg_stage2_9637;
				e1_9637_stage3_9637<= e1_9637_stage2_9637;
				e2_9637_stage3_9637<= e2_9637_stage2_9637;

				
				end
			end
				
			else if(m1_shift>m2_second_stage)
			begin
				if(s1_9637_reg_stage2_9637!=s2_9637_reg_stage2_9637)
				begin
				m1_shiftmore_stage3_9637 <= m1_shift;
				m2_2comp_m2 <= (~m2_second_stage + 1'b1); //2's compliment of m1
				s1_9637_reg_stage3_9637 <=s1_9637_reg_stage2_9637;
				s2_9637_reg_stage3_9637 <=s2_9637_reg_stage2_9637;
				e1_9637_stage3_9637<= e1_9637_stage2_9637;
				e2_9637_stage3_9637<= e2_9637_stage2_9637;

				
				end
				
				begin
				m1_shiftmore_stage3_9637 <= m1_shift;
				m2_less_stage3_9637 <= m2_second_stage;
				s1_9637_reg_stage3_9637 <=s1_9637_reg_stage2_9637;
				s2_9637_reg_stage3_9637 <=s2_9637_reg_stage2_9637;
				e1_9637_stage3_9637<= e1_9637_stage2_9637;
				e2_9637_stage3_9637<= e2_9637_stage2_9637;

				
				end
			end
				
			else if(m1_shift<m2_second_stage)     // ##### Example 3 stage 3 these come in 4th cycle
			begin
				$display("e2_9637_reg=%b Eg Stage 3 ####@@@@@ start", m2_second_stage);
				
				m2_shift_less_stage3_9637 <= m2_second_stage;
				$display("e2_9637_reg=%b Eg Stage 3 start", m2_shift_less_stage3_9637);
				if(s1_9637_reg_stage2_9637!=s2_9637_reg_stage2_9637)
				begin
				m1_2comp_m1_shift <= (~m1_shift + 1'b1); //2's compliment of m1
				$display("e2_9637_reg=%b Eg Stage 3 2's Comp", m2_shift_less_stage3_9637);
				
				s1_9637_reg_stage3_9637 <=s1_9637_reg_stage2_9637;
				s2_9637_reg_stage3_9637 <=s2_9637_reg_stage2_9637;
				e1_9637_stage3_9637<= e1_9637_stage2_9637;
				e2_9637_stage3_9637<= e2_9637_stage2_9637;

				
				end
				
				else
				begin
				//m2_shift_less_stage3_9637 <= m2_second_stage;   //##### Example 1 stage 3
				m1_shift_less_stage3_9637 <= m1_shift;
				s1_9637_reg_stage3_9637 <=s1_9637_reg_stage2_9637;
				s2_9637_reg_stage3_9637 <=s2_9637_reg_stage2_9637;
				e1_9637_stage3_9637<= e1_9637_stage2_9637;
				e2_9637_stage3_9637<= e2_9637_stage2_9637;

				
				end
			end
			
			else if (m2_no_shift > m1_no_shift)
				begin
					if(s1_9637_reg_stage2_9637!=s2_9637_reg_stage2_9637)
					begin
					m2_no_shift_stage3_9637 <= m2_no_shift;
					m1_2comp_m1_no_shift <= (~m1_no_shift + 1'b1); //2's compliment of m1
					s1_9637_reg_stage3_9637 <=s1_9637_reg_stage2_9637;
					s2_9637_reg_stage3_9637 <=s2_9637_reg_stage2_9637;
					e1_9637_stage3_9637<= e1_9637_stage2_9637;
					e2_9637_stage3_9637<= e2_9637_stage2_9637;

				
					end
					
					else
					begin
					m2_no_shift_stage3_9637 <= m2_no_shift;
					m1_no_shift_again <= m1_no_shift;
					s1_9637_reg_stage3_9637 <=s1_9637_reg_stage2_9637;
				    s2_9637_reg_stage3_9637 <=s2_9637_reg_stage2_9637;
					e1_9637_stage3_9637<= e1_9637_stage2_9637;
					e2_9637_stage3_9637<= e2_9637_stage2_9637;

				
					end
				
				end
				
			else if (m2_no_shift < m1_no_shift)
				begin
					if(s1_9637_reg_stage2_9637!=s2_9637_reg_stage2_9637)
					begin
					m1_no_shift_stage3_9637 <= m1_no_shift;
					m2_2comp_m1_no_shift <= (~m2_no_shift + 1'b1); //2's compliment of m1
					s1_9637_reg_stage3_9637 <=s1_9637_reg_stage2_9637;
				    s2_9637_reg_stage3_9637 <=s2_9637_reg_stage2_9637;
					e1_9637_stage3_9637<= e1_9637_stage2_9637;
					e2_9637_stage3_9637<= e2_9637_stage2_9637;

				
					end
					
					else
					begin
					m1_no_shift_stage3_9637 <= m1_no_shift;
					m2_no_shift_again <= m2_no_shift;
					s1_9637_reg_stage3_9637 <=s1_9637_reg_stage2_9637;
				    s2_9637_reg_stage3_9637 <=s2_9637_reg_stage2_9637;
					e1_9637_stage3_9637<= e1_9637_stage2_9637;
					e2_9637_stage3_9637<= e2_9637_stage2_9637;

				
					end
				
				end	

		end			
	end
	
	
//stage 4 : Add the two mantissas. Then, determine the amount of shifts required and the corresponding direction to normalize the result (normalization-1).
always@(posedge clk or negedge reset)
	begin
			
		if(!reset)
		begin
			s1_9637_reg= 0; s2_9637_reg= 0; e1_9637_reg = 0; e2_9637_reg = 0; m1_reg= 0; m2_reg= 0;
		end
		
		else
		begin		
			if(m2_2comp_m2_shift)
				begin
					m3_9637 <= m1+ m2_2comp_m2_shift;
					s1_9637_reg_stage4 <=s1_9637_reg_stage3_9637;
				    s2_9637_reg_stage4 <=s2_9637_reg_stage3_9637;
					e1_9637_stage4<= e1_9637_stage3_9637;
					e2_9637_stage4<= e2_9637_stage3_9637;

				end
				
			else if(m1_2comp_m1)
				begin
					m3_9637 <= m2_shift_stage3_9637 + m1_2comp_m1;
					s1_9637_reg_stage4 <=s1_9637_reg_stage3_9637;
				    s2_9637_reg_stage4 <=s2_9637_reg_stage3_9637;
					e1_9637_stage4<= e1_9637_stage3_9637;
					e2_9637_stage4<= e2_9637_stage3_9637;

				end
				
			else if(m2_2comp_m2)
				begin
					m3_9637 <= m1_shift+m2_2comp_m2; 
					e3_9637 <= e1_9637;
					s1_9637_reg_stage4 <=s1_9637_reg_stage3_9637;
				    s2_9637_reg_stage4 <=s2_9637_reg_stage3_9637;
					e1_9637_stage4<= e1_9637_stage3_9637;
					e2_9637_stage4<= e2_9637_stage3_9637;

				end
				
			else if(m1_2comp_m1_shift)
				begin
					m3_9637 <= m1_2comp_m1_shift+m2; 
					s1_9637_reg_stage4 <=s1_9637_reg_stage3_9637;
				    s2_9637_reg_stage4 <=s2_9637_reg_stage3_9637;
					e1_9637_stage4<= e1_9637_stage3_9637;
					e2_9637_stage4<= e2_9637_stage3_9637;

				end

				
			else if(m1_shift_less_stage3_9637)
				begin
					m3_9637 <= m2_shift_less_stage3_9637+m1_shift_less_stage3_9637; 
					s1_9637_reg_stage4 <=s1_9637_reg_stage3_9637;
				    s2_9637_reg_stage4 <=s2_9637_reg_stage3_9637;
					e1_9637_stage4<= e1_9637_stage3_9637;
					e2_9637_stage4<= e2_9637_stage3_9637;

				end
				
			else if (m1_2comp_m1_no_shift)
				begin
					m3_9637 <= m2_no_shift_stage3_9637 + m1_2comp_m1_no_shift; 
					
					s1_9637_reg_stage4 <=s1_9637_reg_stage3_9637;
				    s2_9637_reg_stage4 <=s2_9637_reg_stage3_9637;
					e1_9637_stage4<= e1_9637_stage3_9637;
					e2_9637_stage4<= e2_9637_stage3_9637;

				end
				
			else if (m2_2comp_m1_no_shift)
				begin
					m3_9637 <= m1_no_shift_stage3_9637 + m2_2comp_m1_no_shift; 					
					s1_9637_reg_stage4 <=s1_9637_reg_stage3_9637;
				    s2_9637_reg_stage4 <=s2_9637_reg_stage3_9637;
					e1_9637_stage4<= e1_9637_stage3_9637;
					e2_9637_stage4<= e2_9637_stage3_9637;

				end
								

		end
	end			
endmodule




//*************** TestBench Carry Select Adder *************************************************

module PipelineAdderTB();

reg s1_9637,s2_9637;
reg [7:0] e1_9637,e2_9637;
wire [7:0] e3_9637;
reg [22:0] mantissa1_9637,mantissa2_9637;
wire [23:0] m3_9637;
reg clk=1'b1, reset;

always #1 clk=~clk;

PipelineAdder inst1(s1_9637,s2_9637,e1_9637,e2_9637,e3_9637,mantissa1_9637,mantissa2_9637,m3_9637,clk,reset);

initial begin
	$dumpfile ("AdderIEEE.vcd");
	$dumpvars (0);
//$monitor("m1=%b, m2=%b, e1_9637=%b, e2_9637=%b , m3_9637=%b , e3_9637=%b, reset=%b", mantissa1_9637, mantissa2_9637, e1_9637, e2_9637, m3_9637, e3_9637, reset);
  
	s1_9637 = 1'b0;	e1_9637 = 8'b1000_0101;	mantissa1_9637 = 23'b1000_1000_0000_0000_0000_000;	reset = 1'b1; //98
	s2_9637 = 1'b0;	e2_9637 = 8'b1000_0110;	mantissa2_9637 = 23'b0101_0010_0000_0000_0000_000;	reset = 1'b1; //169
	#2;

	s1_9637 = 1'b0;	e1_9637 = 8'b1000_0101;	mantissa1_9637 = 23'b1000_1100_0000_0000_0000_000;	reset = 1'b1; //99
	s2_9637 = 1'b1;	e2_9637 = 8'b1000_0101;	mantissa2_9637 = 23'b0110_0100_0000_0000_0000_000;	reset = 1'b1; //-89
	#2;
 	
 	s1_9637 = 1'b1;	e1_9637 = 8'b1000_0100;	mantissa1_9637 = 23'b0110_1000_0000_0000_0000_000;	reset = 1'b1; //-45
	s2_9637 = 1'b0;	e2_9637 = 8'b1000_0101;	mantissa2_9637 = 23'b0011_1100_0000_0000_0000_000;	reset = 1'b1; //79
	#2;
	
	s1_9637 = 1'b1;	e1_9637 = 8'b1000_0111;	mantissa1_9637 = 23'b0001_1011_0000_0000_0000_000;	reset = 1'b1; //-283
	s2_9637 = 1'b1;	e2_9637 = 8'b1000_0101;	mantissa2_9637 = 23'b0000_1000_0000_0000_0000_000;	reset = 1'b1; //-66
	#2;

	s1_9637 = 1'b0;	e1_9637 = 8'b0000_0000;	mantissa1_9637 = 23'b0000_0000_0000_0000_0000_000;	reset = 1'b1; //0
	s2_9637 = 1'b0;	e2_9637 = 8'b0000_0000;	mantissa2_9637 = 23'b0000_0000_0000_0000_0000_000;	reset = 1'b1; //0
	#2;

	s1_9637 = 1'b0;	e1_9637 = 8'b0000_0000;	mantissa1_9637 = 23'b0000_0000_0000_0000_0000_000;	reset = 1'b1; //0
	s2_9637 = 1'b1;	e2_9637 = 8'b1000_0101;	mantissa2_9637 = 23'b1101_0100_0000_0000_0000_000;	reset = 1'b1; //-117
	#2;
	
	s1_9637 = 1'b1;	e1_9637 = 8'b1000_0101;	mantissa1_9637 = 23'b1011_1000_1000_0000_0000_000;	reset = 1'b1; //-110.125
	s2_9637 = 1'b0;	e2_9637 = 8'b1000_0101;	mantissa2_9637 = 23'b1000_1111_1000_0000_0000_000;	reset = 1'b1; //99.875
	#2;

	s1_9637 = 1'b0;	e1_9637 = 8'b1000_0101;	mantissa1_9637 = 23'b1011_1011_1000_0000_0000_000;	reset = 1'b1; //110.875
	s2_9637 = 1'b0;	e2_9637 = 8'b1000_0101;	mantissa2_9637 = 23'b1000_1100_1000_0000_0000_000;	reset = 1'b1; //99.125
	#2;
	
	s1_9637 = 1'b0;	e1_9637 = 8'b1000_0101;	mantissa1_9637 = 23'b1011_1011_1000_0000_0000_000;	reset = 1'b1; //110.875
	s2_9637 = 1'b0;	e2_9637 = 8'b1000_0101;	mantissa2_9637 = 23'b1000_1100_1000_0000_0000_000;	reset = 1'b1; //99.125
	#2;
	
	s1_9637 = 1'b0;	e1_9637 = 8'b1000_0101;	mantissa1_9637 = 23'b1011_1011_1000_0000_0000_000;	reset = 1'b1; //110.875
	s2_9637 = 1'b0;	e2_9637 = 8'b1000_0101;	mantissa2_9637 = 23'b1000_1100_1000_0000_0000_000;	reset = 1'b1; //99.125
	#12;
	

 $finish();	
end

endmodule

AdderIEEE.vcd
$date
	Wed Feb 28 21:41:27 2018
$end

$version
	Synopsys VCS version I-2014.03-2
$end

$timescale
	1ns
$end

$comment Csum: 1 0f748e8bba1eb4ef $end


$scope module PipelineAdderTB $end
$var reg 1 ! s1_9637 $end
$var reg 1 " s2_9637 $end
$var reg 8 # e1_9637 [7:0] $end
$var reg 8 $ e2_9637 [7:0] $end
$var wire 8 % e3_9637 [7:0] $end
$var reg 23 & mantissa1_9637 [22:0] $end
$var reg 23 ' mantissa2_9637 [22:0] $end
$var wire 24 ( m3_9637 [23:0] $end
$var reg 1 ) clk $end
$var reg 1 * reset $end

$scope module inst1 $end
$var wire 1 ! s1_9637 $end
$var wire 1 " s2_9637 $end
$var reg 1 + s1_9637_reg $end
$var reg 1 , s2_9637_reg $end
$var reg 1 - s1_9637_reg_stage1_9637 $end
$var reg 1 . s1_9637_reg_stage2_9637 $end
$var reg 1 / s1_9637_reg_stage3_9637 $end
$var reg 1 0 s1_9637_reg_stage4 $end
$var reg 1 1 s2_9637_reg_stage1_9637 $end
$var reg 1 2 s2_9637_reg_stage2_9637 $end
$var reg 1 3 s2_9637_reg_stage3_9637 $end
$var reg 1 4 s2_9637_reg_stage4 $end
$var wire 8 # e1_9637 [7:0] $end
$var wire 8 $ e2_9637 [7:0] $end
$var reg 8 5 e1_9637_reg [7:0] $end
$var reg 8 6 e2_9637_reg [7:0] $end
$var reg 8 7 e_same [7:0] $end
$var reg 8 8 e1_9637_stage1_9637 [7:0] $end
$var reg 8 9 e1_9637_stage2_9637 [7:0] $end
$var reg 8 : e1_9637_stage3_9637 [7:0] $end
$var reg 8 ; e1_9637_stage4 [7:0] $end
$var reg 8 < e2_9637_stage4 [7:0] $end
$var reg 8 = e2_9637_stage1_9637 [7:0] $end
$var reg 8 > e2_9637_stage2_9637 [7:0] $end
$var reg 8 ? e2_9637_stage3_9637 [7:0] $end
$var reg 8 @ e3_9637 [7:0] $end
$var wire 23 & mantissa1_9637 [22:0] $end
$var wire 23 ' mantissa2_9637 [22:0] $end
$var reg 24 A m1 [23:0] $end
$var reg 24 B m2 [23:0] $end
$var reg 24 C m1_stage1_9637 [23:0] $end
$var reg 24 D m2_stage1_9637 [23:0] $end
$var reg 24 E m4 [23:0] $end
$var reg 24 F m1_2comp [23:0] $end
$var reg 24 G m2_2comp [23:0] $end
$var reg 24 H m1_shift [23:0] $end
$var reg 24 I m2_shift [23:0] $end
$var reg 24 J m1_reg [23:0] $end
$var reg 24 K m2_reg [23:0] $end
$var reg 24 L m2_2comp_m2_shift [23:0] $end
$var reg 24 M m1_2comp_m1 [23:0] $end
$var reg 24 N m2_2comp_m2 [23:0] $end
$var reg 24 O m1_2comp_m1_shift [23:0] $end
$var reg 24 P m1_no_shift [23:0] $end
$var reg 24 Q m2_no_shift [23:0] $end
$var reg 24 R m1_stage3_9637 [23:0] $end
$var reg 24 S m2_stage3_9637 [23:0] $end
$var reg 24 T m2_shift_stage3_9637 [23:0] $end
$var reg 24 U m1_less_stage3_9637 [23:0] $end
$var reg 24 V m2_shift_less_stage3_9637 [23:0] $end
$var reg 24 W m1_shift_less_stage3_9637 [23:0] $end
$var reg 24 X m1_shiftmore_stage3_9637 [23:0] $end
$var reg 24 Y m2_less_stage3_9637 [23:0] $end
$var reg 24 Z m1_no_shift_stage3_9637 [23:0] $end
$var reg 24 [ m2_no_shift_again [23:0] $end
$var reg 24 \ m2_no_shift_stage3_9637 [23:0] $end
$var reg 24 ] m1_no_shift_again [23:0] $end
$var reg 24 ^ m1_2comp_m1_no_shift [23:0] $end
$var reg 24 _ m2_2comp_m1_no_shift [23:0] $end
$var reg 24 ` m1_second_stage [23:0] $end
$var reg 24 a m2_second_stage [23:0] $end
$var reg 24 b m3_9637 [23:0] $end
$var wire 1 ) clk $end
$var wire 1 * reset $end
$upscope $end

$upscope $end

$enddefinitions $end

#0
$dumpvars
1)
1*
0!
x+
0-
x.
x/
x0
0"
x,
01
x2
x3
x4
b10000101 #
b00000001 5
b10000101 8
bxxxxxxxx 9
bxxxxxxxx :
bxxxxxxxx ;
b10000110 $
bxxxxxxxx 6
b10000110 =
bxxxxxxxx >
bxxxxxxxx ?
bxxxxxxxx <
bxxxxxxxx @
bxxxxxxxx 7
bxxxxxxxxxxxxxxxxxxxxxxxx A
bxxxxxxxxxxxxxxxxxxxxxxxx F
bxxxxxxxxxxxxxxxxxxxxxxxx M
bxxxxxxxxxxxxxxxxxxxxxxxx ^
bxxxxxxxxxxxxxxxxxxxxxxxx O
bxxxxxxxxxxxxxxxxxxxxxxxx U
bxxxxxxxxxxxxxxxxxxxxxxxx P
bxxxxxxxxxxxxxxxxxxxxxxxx ]
bxxxxxxxxxxxxxxxxxxxxxxxx Z
bxxxxxxxxxxxxxxxxxxxxxxxx J
bxxxxxxxxxxxxxxxxxxxxxxxx `
bxxxxxxxxxxxxxxxxxxxxxxxx H
bxxxxxxxxxxxxxxxxxxxxxxxx W
bxxxxxxxxxxxxxxxxxxxxxxxx X
b110001000000000000000000 C
bxxxxxxxxxxxxxxxxxxxxxxxx R
bxxxxxxxxxxxxxxxxxxxxxxxx B
bxxxxxxxxxxxxxxxxxxxxxxxx G
bxxxxxxxxxxxxxxxxxxxxxxxx _
bxxxxxxxxxxxxxxxxxxxxxxxx N
bxxxxxxxxxxxxxxxxxxxxxxxx L
bxxxxxxxxxxxxxxxxxxxxxxxx Y
bxxxxxxxxxxxxxxxxxxxxxxxx Q
bxxxxxxxxxxxxxxxxxxxxxxxx [
bxxxxxxxxxxxxxxxxxxxxxxxx \
bxxxxxxxxxxxxxxxxxxxxxxxx K
bxxxxxxxxxxxxxxxxxxxxxxxx a
bxxxxxxxxxxxxxxxxxxxxxxxx I
bxxxxxxxxxxxxxxxxxxxxxxxx V
bxxxxxxxxxxxxxxxxxxxxxxxx T
b101010010000000000000000 D
bxxxxxxxxxxxxxxxxxxxxxxxx S
bxxxxxxxxxxxxxxxxxxxxxxxx b
bxxxxxxxxxxxxxxxxxxxxxxxx E
b10001000000000000000000 &
b01010010000000000000000 '
bxxxxxxxx %
bxxxxxxxxxxxxxxxxxxxxxxxx (
$end
#10
0)
#20
b10001100000000000000000 &
1"
b10000101 $
b01100100000000000000000 '
1)
b011000100000000000000000 H
b101010010000000000000000 a
0.
02
b10000101 9
b10000110 >
b110001100000000000000000 A
b101100100000000000000000 B
b00000000 5
11
b10000101 =
#30
0)
#40
1!
b10000100 #
b01101000000000000000000 &
0"
b00111100000000000000000 '
1)
b101100100000000000000000 I
b110001100000000000000000 `
12
b10000101 >
b101010010000000000000000 V
b011000100000000000000000 W
0/
03
b10000101 :
b10000110 ?
b101101000000000000000000 C
b100111100000000000000000 D
b00000001 5
1-
01
b10000100 8
#50
0)
#60
b10000111 #
b00011011000000000000000 &
1"
b00001000000000000000000 '
1)
b010110100000000000000000 H
b100111100000000000000000 a
1.
02
b10000100 9
b110001100000000000000000 R
b010011100000000000000000 L
13
b10000101 ?
b100011011000000000000000 A
b100001000000000000000000 B
b00000010 5
11
b10000111 8
b000010110000000000000000 b
b000010110000000000000000 (
00
04
b10000101 ;
b10000110 <
#70
0)
#80
0!
b00000000 #
b00000000000000000000000 &
0"
b00000000 $
b00000000000000000000000 '
1)
b001011010000000000000000 H
12
b10000111 9
1/
03
b10000100 :
b100000000000000000000000 A
b100000000000000000000000 B
b00000000 5
0-
01
b00000000 8
b00000000 =
b110110111000000000000000 b
b110110111000000000000000 (
14
b10000101 <
#90
0)
#100
1"
b10000101 $
b11010100000000000000000 '
1)
b100000000000000000000000 I
b100000000000000000000000 `
0.
02
b00000000 9
b00000000 >
b101100100000000000000000 S
13
b10000111 :
b100000000000000000000000 C
b111010100000000000000000 D
b10000101 5
11
b10000101 =
b110011100000000000000000 b
b110011100000000000000000 (
10
04
b10000100 ;
#110
0)
#120
1!
b10000101 #
b10111000100000000000000 &
0"
b10001111100000000000000 '
1)
b000000000000000000000000 H
b111010100000000000000000 a
12
b10000101 >
b100111100000000000000000 V
b001011010000000000000000 W
0/
03
b00000000 :
b00000000 ?
b110111000100000000000000 A
b110001111100000000000000 B
b00000000 5
1-
01
b10000101 8
14
b10000111 ;
#130
0)
#140
0!
b10111011100000000000000 &
b10001100100000000000000 '
1)
b110001111100000000000000 I
b110111000100000000000000 `
1.
02
b10000101 9
b111010100000000000000000 V
b000000000000000000000000 O
13
b10000101 ?
b110111011100000000000000 A
b110001100100000000000000 B
0-
b001010100100000000000000 b
b001010100100000000000000 (
00
04
b00000000 ;
b00000000 <
#150
0)
#160
1)
b110001100100000000000000 I
b110111011100000000000000 `
0.
b110111000100000000000000 R
b001110000100000000000000 L
1/
03
b10000101 :
b001010111100000000000000 b
b001010111100000000000000 (
14
b10000101 <
#170
0)
#180
1)
b110111011100000000000000 R
b110001100100000000000000 S
0/
b000101100000000000000000 b
b000101100000000000000000 (
10
04
b10000101 ;
#190
0)
#200
1)
00
