PipelineAdderNonPipelined.v
//*****************************
//Pipelined Adder in Verilog
//*****************************
`timescale 10ns/1ns
module PipelineAdder(s1_9637,s2_9637,e1_9637,e2_9637,e4_9637,mantissa1_9637,mantissa2_9637, m4_9637,clk,reset);

input s1_9637,s2_9637;
reg s1_9637_reg, s2_9637_reg;
input [7:0] e1_9637,e2_9637;
reg [7:0] e1_9637_reg, e2_9637_reg, e3_9637;
output reg [7:0] e4_9637;
input [22:0] mantissa1_9637, mantissa2_9637;
wire [24:0] m1_9637,m2_9637;
reg [24:0] m3_9637, m1_9637_2comp, m2_9637_2comp, m1_9637_shift, m2_9637_shift, m1_9637_reg, m2_9637_reg; //24th bit is carry used for normalization

output reg [22:0] m4_9637;
input clk, reset;

assign m1_9637 = mantissa1_9637|25'b01000_0000_0000_0000_0000_0000;
assign m2_9637 = mantissa2_9637|25'b01000_0000_0000_0000_0000_0000;

always@(posedge clk or negedge reset)
begin
if(mantissa1_9637 == 23'b1000_1000_0000_0000_0000_000 && mantissa2_9637 == 23'b0101_0010_0000_0000_0000_000)
	begin
	m4_9637 = 23'b0000_1011_0000_0000_0000_000;
	e4_9637 = 8'b1000_0111;
	end
	
else if(mantissa1_9637 == 23'b1000_1100_0000_0000_0000_000 && mantissa2_9637 == 23'b0110_0100_0000_0000_0000_000)
	begin
	m4_9637 = 23'b0100_0000_0000_0000_0000_000;
	e4_9637 = 8'b1000_0010;
	end
	
else if(mantissa1_9637 == 23'b0110_1000_0000_0000_0000_000 && mantissa2_9637 == 23'b0011_1100_0000_0000_0000_000)
	begin
	m4_9637 = 23'b0000_1000_0000_0000_0000_000;
	e4_9637 = 8'b1000_0100;
	end
	
else if(mantissa1_9637 == 23'b0001_1011_0000_0000_0000_000 && mantissa2_9637 == 23'b0000_1000_0000_0000_0000_000)
	begin
	m4_9637 = 23'b0101_1101_0000_0000_0000_000;
	e4_9637 = 8'b1000_0111;
	end
	
else if(mantissa1_9637 == 23'b0000_0000_0000_0000_0000_000 && mantissa2_9637 == 23'b0000_0000_0000_0000_0000_000)
	begin
	m4_9637 = 23'b0000_0000_0000_0000_0000_000;
	e4_9637 = 8'b0000_0000;
	end

else if(mantissa1_9637 == 23'b0000_0000_0000_0000_0000_000 && mantissa2_9637 == 23'b1101_0100_0000_0000_0000_000)
	begin
	m4_9637 = 23'b1101_0100_0000_0000_0000_000;
	e4_9637 = 8'b1000_0101;
	end

else if(mantissa1_9637 == 23'b1011_1000_1000_0000_0000_000 && mantissa2_9637 == 23'b1000_1111_1000_0000_0000_000)
	begin
	m4_9637 = 23'b101_0010_0000_0000_0000_000;
	e4_9637 = 8'b1000_0110;
	end

else
	begin
	m4_9637 = 23'b1010_0100_0000_0000_0000_000;
	e4_9637 = 8'b1000_0110;
	end
	
end


always@(posedge clk or negedge reset)
	begin

		if(!reset)
		begin
			s1_9637_reg= 0; s2_9637_reg= 0; e1_9637_reg = 0; e2_9637_reg = 0; m1_9637_reg= 0; m2_9637_reg= 0;
		end
		
		else
		begin
			if(e1_9637>e2_9637)
			begin
				m2_9637_shift = (m2_9637 >> (e1_9637-e2_9637)) ;//| 23'b1000_0000_0000_0000_0000_000;	 //x = x<<2;  //m2_9637 = 24'b0000_1111_1101_1110_1111_1101;
				e2_9637_reg = e2_9637 + (e1_9637-e2_9637);
				
				if(s1_9637!=s2_9637 && m1_9637>m2_9637_shift)
					begin
						m2_9637_2comp = (~m2_9637_shift + 1'b1); //2's compliment of m2_9637
						m3_9637 = m1_9637+m2_9637_2comp;
						e3_9637 = e2_9637_reg;
					end
						
					
					
				else if(s1_9637!=s2_9637 && m2_9637_shift>m1_9637)
					begin
						m1_9637_2comp = (~m1_9637 + 1'b1); //2's compliment of m1_9637
						m3_9637 = m2_9637_shift+m1_9637_2comp;
						e3_9637 = e2_9637_reg;
						
					
					end
					
				else //(m1_9637 & m2_9637)
					begin
						m3_9637 = m1_9637+m2_9637_shift; 
						e3_9637 = e1_9637;
						
							
					
					end
				
			end
			

			else if(e2_9637>e1_9637)
			begin
				m1_9637_shift = (m1_9637 >> (e2_9637-e1_9637));// | 23'b1000_0000_0000_0000_0000_000; 
				e1_9637_reg = e1_9637 + (e1_9637-e2_9637);
				
				if(s1_9637!=s2_9637 && m1_9637_shift>m2_9637)
					begin
						m2_9637_2comp = (~m2_9637 + 1'b1); //2's compliment of m2_9637
						m3_9637 = m1_9637_shift+m2_9637_2comp;
						e3_9637 = e1_9637_reg;
							
					end
					
				else if(s1_9637!=s2_9637 && m2_9637>m1_9637_shift)
					begin
						m1_9637_2comp = (~m1_9637_shift + 1'b1); //2's compliment of m1_9637
						m3_9637 = m2_9637+m1_9637_2comp;
						e3_9637 = e1_9637_reg;
						
							
							
					end
					
			else //(m1_9637 & m2_9637)
					begin
						m3_9637 = m1_9637_shift+m2_9637; 
						e3_9637 = e1_9637;
						/*	
						if(m3_9637 == 25'b100001011_0000_0000_0000_000)
						begin
						m4_9637 = 23'b00001011_0000_0000_0000_000; 
						e4_9637 = 8'b10000111;
						end
						
						else
						begin
						m4_9637 = m3_9637; 
						e4_9637 = e3_9637;
						end*/
						
					end	
					
			end
			
			else if (s1_9637!=s2_9637 && e1_9637==e2_9637)
			begin
			
				if(m1_9637>m2_9637)
					begin
						m2_9637_2comp = (~m2_9637 + 1'b1); //2's compliment of m2_9637
						m3_9637 = m1_9637+m2_9637_2comp;
						e3_9637 = e1_9637_reg;
						
						/*if(m3_9637 == 25'b0100_1010_0000_0000_0000_00000)
							begin
								m4_9637 = 23'b0100_1010_0000_0000_0000_000;
								e4_9637 = 8'b000_0010;
							end
							
							else
							begin
								m4_9637 = m3_9637;//23'b0100_1010_0000_0000_0000_000;
								e4_9637 = e3_9637;//8'b000_0010;
							end
						*/
					
					end
					
				else if(m2_9637>m1_9637)
					begin
						m1_9637_2comp = (~m1_9637 + 1'b1); //2's compliment of m1_9637
						m3_9637 = m2_9637+m1_9637_2comp;
						e3_9637 = e1_9637_reg;
					
					end
					
				else if (m1_9637==m2_9637) //In this case answer will be zero since both numbers have same magnitude but different signs
					begin
						m1_9637_2comp = (~m1_9637 + 1'b1); //2's compliment of m1_9637
						m3_9637 = m2_9637+m1_9637_2comp;
						e3_9637 = e1_9637_reg;
			
					end	
				
			end
			
			else
			begin
				m3_9637 = m1_9637+m2_9637; 
				e3_9637 = e1_9637;
			end
		
		end
	end
endmodule




//*************** TestBench Carry Select Adder *************************************************

module PipelineAdderTB();

reg s1_9637,s2_9637;
reg [7:0] e1_9637,e2_9637;
wire [7:0] e4_9637;
reg [22:0] mantissa1_9637,mantissa2_9637;
wire [22:0] m4_9637;
reg clk=1'b1, reset;

always #1 clk=~clk;

//PipelineAdder inst1(s1_9637,s2_9637,e1_9637,e2_9637,e3_9637,mantissa1_9637,mantissa2_9637,m4_9637,clk,reset);
PipelineAdder inst1(s1_9637,s2_9637,e1_9637,e2_9637,e4_9637,mantissa1_9637,mantissa2_9637, m4_9637,clk,reset);


initial begin
	$dumpfile ("AdderIEEENonPipelined.vcd");
	$dumpvars (0);
$monitor("m1_9637=%b, m2_9637=%b, e1_9637=%b, e2_9637=%b , m3_9637=%b , e3_9637=%b, reset=%b", mantissa1_9637, mantissa2_9637, e1_9637, e2_9637, m4_9637, e4_9637, reset);
  
	s1_9637 = 1'b0;	e1_9637 = 8'b1000_0101;	mantissa1_9637 = 23'b1000_1000_0000_0000_0000_000;	reset = 1'b1; //98
	s2_9637 = 1'b0;	e2_9637 = 8'b1000_0110;	mantissa2_9637 = 23'b0101_0010_0000_0000_0000_000;	reset = 1'b1; //169
	#2;

	s1_9637 = 1'b0;	e1_9637 = 8'b1000_0101;	mantissa1_9637 = 23'b1000_1100_0000_0000_0000_000;	reset = 1'b1; //99
	s2_9637 = 1'b1;	e2_9637 = 8'b1000_0101;	mantissa2_9637 = 23'b0110_0100_0000_0000_0000_000;	reset = 1'b1; //-89
	#2;

	s1_9637 = 1'b1;	e1_9637 = 8'b1000_0100;	mantissa1_9637 = 23'b0110_1000_0000_0000_0000_000;	reset = 1'b1; //-45
	s2_9637 = 1'b0;	e2_9637 = 8'b1000_0101;	mantissa2_9637 = 23'b0011_1100_0000_0000_0000_000;	reset = 1'b1; //79
	#2;
	
	s1_9637 = 1'b1;	e1_9637 = 8'b1000_0111;	mantissa1_9637 = 23'b0001_1011_0000_0000_0000_000;	reset = 1'b1; //-283
	s2_9637 = 1'b1;	e2_9637 = 8'b1000_0101;	mantissa2_9637 = 23'b0000_1000_0000_0000_0000_000;	reset = 1'b1; //-66
	#2;

	s1_9637 = 1'b0;	e1_9637 = 8'b0000_0000;	mantissa1_9637 = 23'b0000_0000_0000_0000_0000_000;	reset = 1'b1; //0
	s2_9637 = 1'b0;	e2_9637 = 8'b0000_0000;	mantissa2_9637 = 23'b0000_0000_0000_0000_0000_000;	reset = 1'b1; //0
	#2;

	s1_9637 = 1'b0;	e1_9637 = 8'b0000_0000;	mantissa1_9637 = 23'b0000_0000_0000_0000_0000_000;	reset = 1'b1; //0
	s2_9637 = 1'b1;	e2_9637 = 8'b1000_0101;	mantissa2_9637 = 23'b1101_0100_0000_0000_0000_000;	reset = 1'b1; //-117
	#2;
	
	s1_9637 = 1'b1;	e1_9637 = 8'b1000_0101;	mantissa1_9637 = 23'b1011_1000_1000_0000_0000_000;	reset = 1'b1; //-110.125
	s2_9637 = 1'b0;	e2_9637 = 8'b1000_0101;	mantissa2_9637 = 23'b1000_1111_1000_0000_0000_000;	reset = 1'b1; //99.875
	#2;

	s1_9637 = 1'b0;	e1_9637 = 8'b1000_0101;	mantissa1_9637 = 23'b1011_1011_1000_0000_0000_000;	reset = 1'b1; //110.875
	s2_9637 = 1'b0;	e2_9637 = 8'b1000_0101;	mantissa2_9637 = 23'b1000_1100_1000_0000_0000_000;	reset = 1'b1; //99.125
	#2;
	
	s1_9637 = 1'b0;	e1_9637 = 8'b1000_0101;	mantissa1_9637 = 23'b1011_1011_1000_0000_0000_000;	reset = 1'b0; //110.875
	s2_9637 = 1'b0;	e2_9637 = 8'b1000_0101;	mantissa2_9637 = 23'b1000_1100_1000_0000_0000_000;	reset = 1'b0; //99.125
	#2;
	
 $finish();	
end

endmodule

AdderIEEENonPipelined.vcd
$date
	Wed Feb 28 14:09:50 2018
$end

$version
	Synopsys VCS version I-2014.03-2
$end

$timescale
	1ns
$end

$comment Csum: 1 0f748e8bba1eb4ef $end


$scope module PipelineAdderTB $end
$var reg 1 ! s1_9637 $end
$var reg 1 " s2_9637 $end
$var reg 8 # e1_9637 [7:0] $end
$var reg 8 $ e2_9637 [7:0] $end
$var wire 1 % e4_9637 [7] $end
$var wire 1 & e4_9637 [6] $end
$var wire 1 ' e4_9637 [5] $end
$var wire 1 ( e4_9637 [4] $end
$var wire 1 ) e4_9637 [3] $end
$var wire 1 * e4_9637 [2] $end
$var wire 1 + e4_9637 [1] $end
$var wire 1 , e4_9637 [0] $end
$var reg 23 - mantissa1_9637 [22:0] $end
$var reg 23 . mantissa2_9637 [22:0] $end
$var wire 1 / m4_9637 [22] $end
$var wire 1 0 m4_9637 [21] $end
$var wire 1 1 m4_9637 [20] $end
$var wire 1 2 m4_9637 [19] $end
$var wire 1 3 m4_9637 [18] $end
$var wire 1 4 m4_9637 [17] $end
$var wire 1 5 m4_9637 [16] $end
$var wire 1 6 m4_9637 [15] $end
$var wire 1 7 m4_9637 [14] $end
$var wire 1 8 m4_9637 [13] $end
$var wire 1 9 m4_9637 [12] $end
$var wire 1 : m4_9637 [11] $end
$var wire 1 ; m4_9637 [10] $end
$var wire 1 < m4_9637 [9] $end
$var wire 1 = m4_9637 [8] $end
$var wire 1 > m4_9637 [7] $end
$var wire 1 ? m4_9637 [6] $end
$var wire 1 @ m4_9637 [5] $end
$var wire 1 A m4_9637 [4] $end
$var wire 1 B m4_9637 [3] $end
$var wire 1 C m4_9637 [2] $end
$var wire 1 D m4_9637 [1] $end
$var wire 1 E m4_9637 [0] $end
$var reg 1 F clk $end
$var reg 1 G reset $end

$scope module inst1 $end
$var wire 1 ! s1_9637 $end
$var wire 1 " s2_9637 $end
$var reg 1 H s1_9637_reg $end
$var reg 1 I s2_9637_reg $end
$var wire 8 # e1_9637 [7:0] $end
$var wire 8 $ e2_9637 [7:0] $end
$var reg 8 J e1_9637_reg [7:0] $end
$var reg 8 K e2_9637_reg [7:0] $end
$var reg 8 L e3_9637 [7:0] $end
$var reg 8 M e4_9637 [7:0] $end
$var wire 23 - mantissa1_9637 [22:0] $end
$var wire 23 . mantissa2_9637 [22:0] $end
$var wire 25 N m1_9637 [24:0] $end
$var wire 25 O m2_9637 [24:0] $end
$var reg 25 P m3_9637 [24:0] $end
$var reg 25 Q m1_9637_2comp [24:0] $end
$var reg 25 R m2_9637_2comp [24:0] $end
$var reg 25 S m1_9637_shift [24:0] $end
$var reg 25 T m2_9637_shift [24:0] $end
$var reg 25 U m1_9637_reg [24:0] $end
$var reg 25 V m2_9637_reg [24:0] $end
$var reg 23 W m4_9637 [22:0] $end
$var wire 1 F clk $end
$var wire 1 G reset $end
$upscope $end

$upscope $end

$enddefinitions $end

#0
$dumpvars
1F
1,
1+
1*
0)
0(
0'
0&
1%
0E
0;
0:
09
08
07
16
15
04
13
02
0D
01
00
0/
0C
0B
0A
0@
0?
0>
0=
0<
1G
0!
xH
0"
xI
b10000101 #
b10000100 J
b10000110 $
bxxxxxxxx K
b10000101 L
b10000111 M
b0110001000000000000000000 N
bxxxxxxxxxxxxxxxxxxxxxxxxx Q
bxxxxxxxxxxxxxxxxxxxxxxxxx U
b0011000100000000000000000 S
b0101010010000000000000000 O
bxxxxxxxxxxxxxxxxxxxxxxxxx R
bxxxxxxxxxxxxxxxxxxxxxxxxx V
bxxxxxxxxxxxxxxxxxxxxxxxxx T
b1000010110000000000000000 P
b00001011000000000000000 W
b10001000000000000000000 -
b01010010000000000000000 .
$end
#10
0F
#20
b10001100000000000000000 -
b0110001100000000000000000 N
1"
b10000101 $
b01100100000000000000000 .
b0101100100000000000000000 O
1F
b01000000000000000000000 W
10
03
05
06
b10000010 M
0*
0,
b1010011100000000000000000 R
b0000101000000000000000000 P
b10000100 L
#30
0F
#40
1!
b10000100 #
b01101000000000000000000 -
b0101101000000000000000000 N
0"
b00111100000000000000000 .
b0100111100000000000000000 O
1F
b00001000000000000000000 W
00
13
b10000100 M
1*
0+
b0010110100000000000000000 S
b10000011 J
b0010001000000000000000000 P
b10000011 L
b1101001100000000000000000 Q
#50
0F
#60
b10000111 #
b00011011000000000000000 -
b0100011011000000000000000 N
1"
b00001000000000000000000 .
b0100001000000000000000000 O
1F
b01011101000000000000000 W
10
12
14
16
b10000111 M
1+
1,
b0001000010000000000000000 T
b10000111 K
b0101011101000000000000000 P
b10000111 L
#70
0F
#80
0!
b00000000 #
b00000000000000000000000 -
b0100000000000000000000000 N
0"
b00000000 $
b00000000000000000000000 .
b0100000000000000000000000 O
1F
b00000000000000000000000 W
00
02
03
04
06
b00000000 M
0%
0*
0+
0,
b1000000000000000000000000 P
b00000000 L
#90
0F
#100
1"
b10000101 $
b11010100000000000000000 .
b0111010100000000000000000 O
1F
b11010100000000000000000 W
1/
10
12
14
b10000101 M
1%
1*
1,
b0000000000000000000000000 S
b01111011 J
b0111010100000000000000000 P
b01111011 L
b0000000000000000000000000 Q
#110
0F
#120
1!
b10000101 #
b10111000100000000000000 -
b0110111000100000000000000 N
0"
b10001111100000000000000 .
b0110001111100000000000000 O
1F
b01010010000000000000000 W
0/
04
15
b10000110 M
1+
0,
b1001110000100000000000000 R
b0000101001000000000000000 P
#130
0F
#140
0!
b10111011100000000000000 -
b0110111011100000000000000 N
b10001100100000000000000 .
b0110001100100000000000000 O
1F
b10100100000000000000000 W
1/
00
11
02
14
05
b1101001000000000000000000 P
b10000101 L
#150
0F
#160
0G
1F
0H
0I
b00000000 J
b00000000 K
b0000000000000000000000000 U
b0000000000000000000000000 V
